johnson/__init__.py
johnson/main.py
johnson-0.1.1.dist-info/entry_points.txt
johnson-0.1.1.dist-info/LICENSE
johnson-0.1.1.dist-info/WHEEL
johnson-0.1.1.dist-info/METADATA
johnson-0.1.1.dist-info/RECORD
