Metadata-Version: 2.1
Name: johnson
Version: 0.1.1
Summary: A simple CLI pretty .json viewer
Home-page: https://github.com/sjlva/johnson
License: MIT
Author: sjlva
Author-email: rafaelsilva@posteo.net
Requires-Python: >=3.8,<4.0
Classifier: License :: OSI Approved :: MIT License
Classifier: Programming Language :: Python :: 3
Classifier: Programming Language :: Python :: 3.10
Classifier: Programming Language :: Python :: 3.8
Classifier: Programming Language :: Python :: 3.9
Requires-Dist: rich[all] (>=12.4.4,<13.0.0)
Requires-Dist: typer[all] (>=0.4.1,<0.5.0)
Project-URL: Repository, https://github.com/sjlva/johnson
